[
  {
    "title": "Opening Day of Baseball at Flanker",
    "date": "March 25 @ 5:00 pm - 11:00 pm",
    "description": "Celebrate the start of baseball season at Flanker with delicious game day bites, local beers, and...",
    "image": "https://atthegateway.com/wp-content/uploads/2026/03/Flanker-opening-day-baseball.jpg"
  },
  {
    "title": "Flanker Full Court Nights",
    "date": "March 25 @ 7:00 pm",
    "description": "Flanker is the place to be to gear up for Jazz game days.",
    "image": "https://atthegateway.com/wp-content/uploads/2026/03/Mar-25-960x640-1.jpg"
  },
  {
    "title": "Flanker Tusks Up Nights",
    "date": "March 26 @ 7:00 pm",
    "description": "Head to Flanker to enjoy the Utah Mammoth game with drinks, game-day bites, and more!",
    "image": "https://atthegateway.com/wp-content/uploads/2026/03/TUSKS-UP_3_26_26.jpg"
  },
  {
    "title": "Hidden Boot Saloon Friday Nights",
    "date": "March 27 @ 5:00 pm - March 28 @ 1:00 am",
    "description": "Start your weekend off right with an evening at the Hidden Boot Saloon.",
    "image": "https://atthegateway.com/wp-content/uploads/2026/03/hbs-friday-nights.jpg"
  },
  {
    "title": "Flanker Full Court Nights",
    "date": "March 27 @ 7:00 pm",
    "description": "Flanker is the place to be to gear up for Jazz game days.",
    "image": "https://atthegateway.com/wp-content/uploads/2026/03/Mar-27-960x640-1.jpg"
  },
  {
    "title": "Bunny Breakfast at Dave & Buster\u2019s",
    "date": "March 28 @ 10:00 am - 12:00 pm",
    "description": "Enjoy a fun Easter breakfast celebration at Dave & Buster's!",
    "image": "https://atthegateway.com/wp-content/uploads/2026/03/bunny-upshow.png"
  },
  {
    "title": "Flanker Tusks Up Nights",
    "date": "March 28 @ 7:00 pm",
    "description": "Head to Flanker to enjoy the Utah Mammoth game with drinks, game-day bites, and more!",
    "image": "https://atthegateway.com/wp-content/uploads/2026/03/Tusks-Up_3_28_26.jpg"
  },
  {
    "title": "Flanker Full Court Nights",
    "date": "March 28 @ 8:00 pm",
    "description": "Flanker is the place to be to gear up for Jazz game days.",
    "image": "https://atthegateway.com/wp-content/uploads/2026/03/Mar-28-960x640-1.jpg"
  },
  {
    "title": "Hidden Boot Saloon Saturday Nights",
    "date": "March 28 @ 10:00 pm - March 29 @ 1:00 am",
    "description": "Head to Flanker for a fun western night filled with music, food, drinks, and more!",
    "image": "https://atthegateway.com/wp-content/uploads/2026/02/Jaime_Henrique-3_28_26-960x640-Gateway.jpg"
  }
]